festutimetable/FestuApi.py
festutimetable/FestuDayTimetable.py
festutimetable/FestuTimetable.py
festutimetable/GroupIds.py
festutimetable/Lecture.py
festutimetable/Utils.py
festutimetable/__init__.py
festutimetable-1.2.0.dist-info/licenses/LICENSE
festutimetable-1.2.0.dist-info/METADATA
festutimetable-1.2.0.dist-info/WHEEL
festutimetable-1.2.0.dist-info/top_level.txt
festutimetable-1.2.0.dist-info/RECORD
