Metadata-Version: 2.4
Name: festutimetable
Version: 1.2.0
Summary: Library for easy requests and use FESTU timetables
Author-email: Onii-Chan <skobochki.ad@mail.ru>
License: MIT
Project-URL: Repository, https://github.com/SerJo2/festutimetable-lib
Project-URL: Issues, https://github.com/SerJo2/festutimetable-lib/issues
Project-URL: Changelog, https://github.com/SerJo2/festutimetable-lib/blob/master/CHANGELOG.md
Keywords: FESTU,requests
Classifier: Development Status :: 5 - Production/Stable
Classifier: Intended Audience :: Developers
Classifier: Intended Audience :: Information Technology
Classifier: Intended Audience :: Other Audience
Classifier: Topic :: Internet
Classifier: Programming Language :: Python :: 3
Classifier: Programming Language :: Python :: 3.10
Classifier: Programming Language :: Python :: 3.11
Classifier: Programming Language :: Python :: 3.12
Requires-Python: >=3.10
License-File: LICENSE
Requires-Dist: requests>=2.32.5
Requires-Dist: beautifulsoup4>=4.14.2
Provides-Extra: test
Requires-Dist: pytest>=6.0; extra == "test"
Dynamic: license-file
